library/Client.py
library/__init__.py
library/version.py
tests/__init__.py
tests/test_myfunction.py
ukrit-0.0.2.dist-info/LICENSE.md
ukrit-0.0.2.dist-info/METADATA
ukrit-0.0.2.dist-info/WHEEL
ukrit-0.0.2.dist-info/top_level.txt
ukrit-0.0.2.dist-info/RECORD
